{
  "patches": [
    {
      "target": "base:student_union",
      "add_screens": [
        {
          "tab_id": "fae_lineage_social",
          "display_name": "Fae Social Work",
          "description": "Social activities that reward charisma and perception while testing normalcy.",
          "backend_class": "ActivityBoardBackend",
          "screen_title": "Fae Social Work",
          "tags": [
            "fae_lineage"
          ],
          "location_filter": "base:student_union"
        }
      ],
      "set": {
        "entities_present": [
          "omni:fae_lineage:lark"
        ]
      }
    }
  ]
}
